membrane_toolkit/__init__.py
membrane_toolkit/__pycache__/__init__.cpython-38.pyc
membrane_toolkit/core/__init__.py
membrane_toolkit/core/diffusion.py
membrane_toolkit/core/donnan.py
membrane_toolkit/core/flory_huggins.py
membrane_toolkit/core/manning.py
membrane_toolkit/core/permeability.py
membrane_toolkit/core/potential.py
membrane_toolkit/core/unitized.py
membrane_toolkit/core/water_uptake.py
membrane_toolkit/core/__pycache__/__init__.cpython-38.pyc
membrane_toolkit/core/__pycache__/diffusion.cpython-38.pyc
membrane_toolkit/core/__pycache__/donnan.cpython-38.pyc
membrane_toolkit/core/__pycache__/flory_huggins.cpython-38.pyc
membrane_toolkit/core/__pycache__/manning.cpython-38.pyc
membrane_toolkit/core/__pycache__/permeability.cpython-38.pyc
membrane_toolkit/core/__pycache__/potential.cpython-38.pyc
membrane_toolkit/core/__pycache__/unitized.cpython-38.pyc
membrane_toolkit/core/__pycache__/water_uptake.cpython-38.pyc
membrane_toolkit/core/tests/test_diffusion.py
membrane_toolkit/core/tests/test_donnan.py
membrane_toolkit/core/tests/test_manning.py
membrane_toolkit/core/tests/test_potential.py
membrane_toolkit/core/tests/test_unitized.py
membrane_toolkit/core/tests/__pycache__/test_diffusion.cpython-38-pytest-5.3.5.pyc
membrane_toolkit/core/tests/__pycache__/test_diffusion.cpython-38-pytest-5.4.1.pyc
membrane_toolkit/core/tests/__pycache__/test_donnan.cpython-38-pytest-5.3.5.pyc
membrane_toolkit/core/tests/__pycache__/test_donnan.cpython-38-pytest-5.4.1.pyc
membrane_toolkit/core/tests/__pycache__/test_manning.cpython-38-pytest-5.3.5.pyc
membrane_toolkit/core/tests/__pycache__/test_manning.cpython-38-pytest-5.4.1.pyc
membrane_toolkit/core/tests/__pycache__/test_potential.cpython-38-pytest-5.3.5.pyc
membrane_toolkit/core/tests/__pycache__/test_potential.cpython-38-pytest-5.4.1.pyc
membrane_toolkit/core/tests/__pycache__/test_unitized.cpython-38-pytest-5.3.5.pyc
membrane_toolkit/core/tests/__pycache__/test_unitized.cpython-38-pytest-5.4.1.pyc
membrane_toolkit-0.1.0.dist-info/LICENSE
membrane_toolkit-0.1.0.dist-info/METADATA
membrane_toolkit-0.1.0.dist-info/WHEEL
membrane_toolkit-0.1.0.dist-info/top_level.txt
membrane_toolkit-0.1.0.dist-info/RECORD
