Metadata-Version: 2.1
Name: membrane-toolkit
Version: 0.1.0
Summary: Python tools for membrane science
Home-page: https://github.com/rkingsbury/membrane-toolkit
Author: Ryan Kingsbury
Author-email: RyanSKingsbury@alumni.unc.edu
License: BSD 3-clause license
Platform: UNKNOWN
Classifier: Programming Language :: Python :: 3
Classifier: Development Status :: 3 - Alpha
Classifier: Environment :: Console
Classifier: Intended Audience :: Science/Research
Classifier: License :: OSI Approved :: BSD License
Classifier: Operating System :: OS Independent
Classifier: Topic :: Software Development :: Libraries :: Python Modules
Requires-Dist: numpy (>=1.14.3)
Requires-Dist: monty (>=3.0.2)
Requires-Dist: maggma (>=0.19)
Requires-Dist: pint (>=0.11)
Requires-Dist: openpyxl
Requires-Dist: pandas
